MANIFEST.in
license.md
readme.md
setup.cfg
setup.py
SpectronPy.egg-info/PKG-INFO
SpectronPy.egg-info/SOURCES.txt
SpectronPy.egg-info/dependency_links.txt
SpectronPy.egg-info/requires.txt
SpectronPy.egg-info/top_level.txt
lib/__init__.py
lib/application.py
lib/assertions.py
lib/configuration.py
lib/driver.py
lib/element.py
lib/exception.py
lib/expected.py
lib/finders.py
lib/globals.py
lib/helper.py
lib/logging.py
lib/matchers.py
lib/query.py
lib/result.py