Metadata-Version: 2.1
Name: SpectronPy
Version: 0.1.3
Home-page: https://github.com/nils-e/SpectronPy
Author: Nils
License: MIT
Keywords: spectronpy spectron electron python selenium webdriver
Requires-Python: >=3.10
License-File: license.md
